sdccli/__init__.py
sdccli/cli/__init__.py
sdccli/cli/alert.py
sdccli/cli/backup.py
sdccli/cli/capture.py
sdccli/cli/command.py
sdccli/cli/compliance.py
sdccli/cli/dashboard/__init__.py
sdccli/cli/dashboard/panel.py
sdccli/cli/dashboardv2.py
sdccli/cli/event.py
sdccli/cli/eventv1.py
sdccli/cli/formatter/__init__.py
sdccli/cli/formatter/json_formatter/__init__.py
sdccli/cli/formatter/text_formatter/__init__.py
sdccli/cli/formatter/text_formatter/alert.py
sdccli/cli/formatter/text_formatter/dashboard.py
sdccli/cli/formatter/text_formatter/panel.py
sdccli/cli/formatter/text_formatter/policy_events.py
sdccli/cli/formatter/text_formatter/scanning/__init__.py
sdccli/cli/formatter/text_formatter/scanning/alert.py
sdccli/cli/formatter/text_formatter/scanning/image.py
sdccli/cli/formatter/text_formatter/scanning/vulnerability.py
sdccli/cli/policy/__init__.py
sdccli/cli/policy/falco_list.py
sdccli/cli/policy/falco_macro.py
sdccli/cli/policy/rule.py
sdccli/cli/profile.py
sdccli/cli/scanning/__init__.py
sdccli/cli/scanning/alert.py
sdccli/cli/scanning/cve_report.py
sdccli/cli/scanning/image.py
sdccli/cli/scanning/policy.py
sdccli/cli/scanning/query.py
sdccli/cli/scanning/registry.py
sdccli/cli/scanning/repo.py
sdccli/cli/scanning/runtime.py
sdccli/cli/scanning/subscription.py
sdccli/cli/scanning/vulnerability/__init__.py
sdccli/cli/scanning/vulnerability/bundle.py
sdccli/cli/settings/__init__.py
sdccli/cli/settings/access_key.py
sdccli/cli/settings/notification.py
sdccli/cli/settings/team.py
sdccli/cli/settings/user.py
sdccli/config.py
sdccli/drop.py
sdccli/falco_macro.py
sdccli/helpers.py
sdccli/printer.py
sdccli/restore.py
sdccli/time.py
sdccli/usecases/__init__.py
sdccli/usecases/alert.py
sdccli/usecases/backup/Pipfile
sdccli/usecases/backup/__init__.py
sdccli/usecases/backup/dump.py
sdccli/usecases/backup/restore.py
sdccli/usecases/dashboard/__init__.py
sdccli/usecases/dashboard/dashboard_v2.py
sdccli/usecases/dashboard/dashboard_v3.py
sdccli/usecases/dashboard/panel.py
sdccli-0.8.2.dist-info/LICENSE.txt
sdccli-0.8.2.dist-info/METADATA
sdccli-0.8.2.dist-info/WHEEL
sdccli-0.8.2.dist-info/entry_points.txt
sdccli-0.8.2.dist-info/RECORD
