Metadata-Version: 2.1
Name: sdccli
Version: 0.8.2
Summary: CLI client for Sysdig Cloud
License: MIT
Author: Sysdig Inc.
Author-email: info@sysdig.com
Maintainer: Nestor Salceda
Maintainer-email: nestor.salceda@sysdig.com
Requires-Python: >=3.6,<4.0
Classifier: License :: OSI Approved :: MIT License
Classifier: Programming Language :: Python :: 3
Classifier: Programming Language :: Python :: 3.6
Classifier: Programming Language :: Python :: 3.7
Classifier: Programming Language :: Python :: 3.8
Classifier: Programming Language :: Python :: 3.9
Classifier: Programming Language :: Python :: 3.10
Classifier: Programming Language :: Python :: 3.11
Requires-Dist: click (>=8.0.1,<9.0.0)
Requires-Dist: httmock (>=1.4.0,<2.0.0)
Requires-Dist: prettytable (>=2,<3)
Requires-Dist: python-dateutil (>=2.8.1,<3.0.0)
Requires-Dist: pyyaml (>=6.0.1,<7.0.0)
Requires-Dist: requests (>=2,<3)
Requires-Dist: sdcclient (>=0.17.0,<0.18.0)
Project-URL: Documentation, https://sysdiglabs.github.io/sysdig-platform-cli/
